pyrception/__init__.py
pyrception-0.2.5.dist-info/licenses/LICENCE.md
pyrception-0.2.5.dist-info/METADATA
pyrception-0.2.5.dist-info/WHEEL
pyrception-0.2.5.dist-info/entry_points.txt
pyrception-0.2.5.dist-info/top_level.txt
pyrception-0.2.5.dist-info/RECORD
